{"community_projects.md":"C7SC3Bzj","docs_1.1-quickstarted.md":"YinHE5uT","docs_1.2-explanationofterms.md":"CuctChIv","docs_2.1-integration.md":"CSTLkgUM","docs_2.2-integratedinterfaceoverview.md":"CdNwuYID","docs_2.3-callbackprotocol.md":"DurCNoR_","docs_2.4-controlmethods.md":"xRkq-dEZ","docs_3.1-pipelineprotocol.md":"BiYZtZPa","docs_3.2-projectinterface.md":"cETjaWVw","docs_3.3-projectinterfacev2.md":"D2SOKTwG","docs_4.1-buildguide.md":"Cqx-Zcow","docs_4.2-standardizedinterfacedesign.md":"AYb1iI08","docs_nodejs_j1.1-quickstarted.md":"xc1gpHoI","docs_nodejs_j1.2-custom recognition and action.md":"CXX5RFJU","docs_nodejs_j1.3-packaging.md":"BL53266L","en_community_projects.md":"7mMpOK9a","en_docs_1.1-quickstarted.md":"CgULc7Vx","en_docs_1.2-explanationofterms.md":"UsKXofP6","en_docs_2.1-integration.md":"CgkKr4pj","en_docs_2.2-integratedinterfaceoverview.md":"CM9GghXL","en_docs_2.3-callbackprotocol.md":"B1EE-ni4","en_docs_2.4-controlmethods.md":"DoLFXhjJ","en_docs_3.1-pipelineprotocol.md":"Bd3OWGNz","en_docs_3.2-projectinterface.md":"0ItaL0Uj","en_docs_3.3-projectinterfacev2.md":"BDO5_JJ8","en_docs_4.1-buildguide.md":"B66qa-te","en_docs_4.2-standardizedinterfacedesign.md":"B4zspJgE","en_docs_nodejs_j1.1-quickstarted.md":"Dd9vMik0","en_docs_nodejs_j1.2-custom recognition and action.md":"D9yZW-dd","en_docs_nodejs_j1.3-packaging.md":"fd5mbYQx","en_index.md":"J7PMKMoP","index.md":"XbnCcCJQ"}
